inventory/__init__.py
inventory/inventory.py
inventory/sql.py
inventory/static/css/bootstrap.min.css
inventory/static/css/common.css
inventory/static/css/dataTables.bootstrap.min.css
inventory/static/css/fixedHeader.bootstrap.min.css
inventory/static/fonts/glyphicons-halflings-regular.eot
inventory/static/fonts/glyphicons-halflings-regular.svg
inventory/static/fonts/glyphicons-halflings-regular.ttf
inventory/static/fonts/glyphicons-halflings-regular.woff
inventory/static/fonts/glyphicons-halflings-regular.woff2
inventory/static/js/bootstrap.min.js
inventory/static/js/customer_typeahead.js
inventory/static/js/dataTables.fixedHeader.min.js
inventory/static/js/filter.js
inventory/static/js/inventory_datatables.js
inventory/static/js/item_typeahead.js
inventory/static/js/jquery-3.2.0.min.js
inventory/static/js/jquery.ba-throttle-debounce.js
inventory/static/js/jquery.dataTables.min.js
inventory/static/js/modal_autofocus.js
inventory/static/js/typeahead.bundle.js
inventory/templates/base.html
inventory/templates/index.html
inventory/templates/index_signed_in.html
inventory/templates/item_detail.html
inventory/templates/order_detail.html
inventory/templates/orders.html
inventory/templates/sale_detail.html
inventory/templates/sales.html
inventory/templates/samples.html
inventory-2.0.1.dist-info/METADATA
inventory-2.0.1.dist-info/RECORD
inventory-2.0.1.dist-info/WHEEL
inventory-2.0.1.dist-info/entry_points.txt
inventory-2.0.1.dist-info/top_level.txt
