Metadata-Version: 2.1
Name: inventory
Version: 2.0.1
Summary: A basic inventory management web app
Home-page: https://github.com/williamjacksn/inventory
Author: William Jackson
Author-email: william@subtlecoolness.com
License: UNKNOWN
Platform: UNKNOWN
Requires-Dist: Flask
Requires-Dist: Flask-OAuth2-Login
Requires-Dist: Flask-SSLify
Requires-Dist: psycopg2
Requires-Dist: waitress
